{"headline":"Öffnungseiten","entries_opening":[{"id":0,"day":"Montag","times1":"7.30 – 13 Uhr","times2":"15 – 19 Uhr"},{"id":1,"day":"Dienstag","times1":"7.30 – 13 Uhr","times2":"15 – 19 Uhr"},{"id":2,"day":"Mittwoch","times1":"7.30 – 14 Uhr","times2":""},{"id":3,"day":"Donnerstag","times1":"7.30 – 13 Uhr","times2":"15 – 19 Uhr"},{"id":4,"day":"Freitag","times1":"7.30 – 16 Uhr","times2":""}],"entries_surgery":[{"id":0,"day":"Montag","times1":"8 – 12 Uhr","times2":"16 – 18 Uhr"},{"id":1,"day":"Dienstag","times1":"8 – 12 Uhr","times2":"16 – 18 Uhr"},{"id":2,"day":"Mittwoch","times1":"8 – 12 Uhr","times2":""},{"id":3,"day":"Donnerstag","times1":"8 – 12 Uhr","times2":"16 – 19 Uhr"},{"id":4,"day":"Freitag","times1":"8 – 12 Uhr","times2":""}]}